netrun/dogfood/__init__.py
netrun/dogfood/auth.py
netrun/dogfood/config.py
netrun/dogfood/py.typed
netrun/dogfood/server.py
netrun/dogfood/models/__init__.py
netrun/dogfood/models/schemas.py
netrun/dogfood/tools/__init__.py
netrun/dogfood/tools/charlotte.py
netrun/dogfood/tools/intirkon.py
netrun/dogfood/tools/meridian.py
netrun/dogfood/tools/netrunsite.py
netrun/dogfood/tools/securevault.py
netrun_dogfood/__init__.py
netrun_dogfood/auth.py
netrun_dogfood/config.py
netrun_dogfood/server.py
netrun_dogfood/models/__init__.py
netrun_dogfood/models/schemas.py
netrun_dogfood/tools/__init__.py
netrun_dogfood/tools/charlotte.py
netrun_dogfood/tools/intirkon.py
netrun_dogfood/tools/meridian.py
netrun_dogfood/tools/netrunsite.py
netrun_dogfood/tools/securevault.py
netrun_dogfood-2.0.0.dist-info/METADATA
netrun_dogfood-2.0.0.dist-info/WHEEL
netrun_dogfood-2.0.0.dist-info/entry_points.txt
netrun_dogfood-2.0.0.dist-info/RECORD
