Metadata-Version: 2.4
Name: netrun-dogfood
Version: 2.0.0
Summary: MCP server providing unified API access to all Netrun Systems products - Dogfood Server
Project-URL: Homepage, https://netrunsystems.com
Project-URL: Documentation, https://docs.netrunsystems.com/dogfood
Project-URL: Repository, https://github.com/netrunsystems/netrun-dogfood
Author-email: Daniel Garza <daniel@netrunsystems.com>
License: MIT
Keywords: api,azure,claude-code,dogfood,mcp,model-context-protocol,netrun
Classifier: Development Status :: 5 - Production/Stable
Classifier: Framework :: Pydantic
Classifier: Framework :: Pydantic :: 2
Classifier: Intended Audience :: Developers
Classifier: License :: OSI Approved :: MIT License
Classifier: Programming Language :: Python :: 3
Classifier: Programming Language :: Python :: 3.10
Classifier: Programming Language :: Python :: 3.11
Classifier: Programming Language :: Python :: 3.12
Classifier: Topic :: Internet :: WWW/HTTP :: HTTP Servers
Classifier: Topic :: Software Development :: Libraries :: Python Modules
Requires-Python: >=3.10
Requires-Dist: httpx>=0.26.0
Requires-Dist: mcp>=1.0.0
Requires-Dist: netrun-auth[azure]>=2.0.0
Requires-Dist: netrun-core>=2.0.0
Requires-Dist: pydantic-settings>=2.1.0
Requires-Dist: pydantic>=2.5.0
Provides-Extra: dev
Requires-Dist: black>=23.12.0; extra == 'dev'
Requires-Dist: mypy>=1.7.0; extra == 'dev'
Requires-Dist: pytest-asyncio>=0.21.0; extra == 'dev'
Requires-Dist: pytest-cov>=4.1.0; extra == 'dev'
Requires-Dist: pytest-mock>=3.12.0; extra == 'dev'
Requires-Dist: pytest>=7.4.0; extra == 'dev'
Requires-Dist: ruff>=0.1.8; extra == 'dev'
